{
  "lastRefreshed": "2026-06-21T15:35:49Z",
  "filters": {
    "minPrice": 7000,
    "maxPrice": 15000,
    "radiusMi": 35,
    "zip": "19063"
  },
  "carscom": {
    "totalFound": 31,
    "url": "https://www.cars.com/shopping/results/?stock_type=used&body_style_slugs[]=convertible&list_price_min=7000&list_price_max=15000&maximum_distance=35&zip=19063&no_accidents=true&clean_title=true&sort=list_price",
    "listings": [
      {
        "id": "81d39f41-5daf-4096-9280-6704c2126b1b",
        "year": 2006,
        "make": "Audi",
        "model": "S4",
        "trim": "quattro AWD 2dr Convertible 6A",
        "price": 7404,
        "mileage": 96924,
        "location": "Warminster, PA",
        "distanceMi": 25,
        "dealer": "PA Auto Liquidators",
        "imageUrl": "https://platform.cstatic-images.com/large/in/v2/002825a0-a9a8-4a84-81f9-2b9f5eb0680e/fe1275b2-6fd0-450b-a535-006d1cb2592b/zgaU1m_CJWUN-2SmM3mrQbOhWDY.jpg",
        "url": "https://www.cars.com/vehicledetail/81d39f41-5daf-4096-9280-6704c2126b1b/",
        "dealRating": null,
        "cleanTitle": true,
        "noAccidents": true,
        "source": "cars.com"
      },
      {
        "id": "c56bf08d-80cc-45af-9113-1b33b52465d3",
        "year": 2015,
        "make": "MINI",
        "model": "Convertible",
        "trim": "Cooper",
        "price": 7904,
        "mileage": 118494,
        "location": "Warminster, PA",
        "distanceMi": 25,
        "dealer": "PA Auto Liquidators",
        "imageUrl": "https://platform.cstatic-images.com/large/in/v2/002825a0-a9a8-4a84-81f9-2b9f5eb0680e/9c9e37b0-7b83-4662-ac14-7c30fa8769ed/h9_bsf8dNMRGzJGAGw8_gi8asH8.jpg",
        "url": "https://www.cars.com/vehicledetail/c56bf08d-80cc-45af-9113-1b33b52465d3/",
        "dealRating": null,
        "cleanTitle": true,
        "noAccidents": true,
        "source": "cars.com"
      },
      {
        "id": "f12cf7c6-8ae1-4690-8661-4f3f45b34d4f",
        "year": 1987,
        "make": "Ford",
        "model": "Mustang",
        "trim": "GT",
        "price": 9500,
        "mileage": 98916,
        "location": "Westville, NJ",
        "distanceMi": 16,
        "dealer": "Corsinos Service Station and Repair Inc",
        "imageUrl": "https://platform.cstatic-images.com/large/in/v2/fba58d6f-4505-4338-955e-5ae6f5b3a641/acbc2a2f-58bc-4c87-8389-4cbd574c25d8/OB6tUeCORiCg507Dt21ZMQOIvH4.jpeg",
        "url": "https://www.cars.com/vehicledetail/f12cf7c6-8ae1-4690-8661-4f3f45b34d4f/",
        "dealRating": null,
        "cleanTitle": true,
        "noAccidents": true,
        "source": "cars.com"
      },
      {
        "id": "5f01dc5a-98a8-41bf-9aad-e79fc5934245",
        "year": 2004,
        "make": "Mercedes-Benz",
        "model": "SL-Class",
        "trim": "2dr Roadster 5.0L",
        "price": 9898,
        "mileage": 53643,
        "location": "Warminster, PA",
        "distanceMi": 25,
        "dealer": "CarsIndex Warminster",
        "imageUrl": "https://platform.cstatic-images.com/large/in/v2/6865b2ba-22d9-5466-9d16-dfe684464f77/13b3373e-98f8-4224-aea2-a29044ff25c0/ADTHCM7ptkyd9Xthmyt-cCze7Ls.jpg",
        "url": "https://www.cars.com/vehicledetail/5f01dc5a-98a8-41bf-9aad-e79fc5934245/",
        "dealRating": null,
        "cleanTitle": true,
        "noAccidents": true,
        "source": "cars.com"
      },
      {
        "id": "fa769e21-a137-4f03-bcdf-7f919e4719d5",
        "year": 2000,
        "make": "BMW",
        "model": "Z3",
        "trim": "2.3 Roadster",
        "price": 9950,
        "mileage": 92293,
        "location": "Feasterville-Trevose, PA",
        "distanceMi": 28,
        "dealer": "Car Cheer",
        "imageUrl": "https://platform.cstatic-images.com/large/in/v2/a733be78-f490-4868-adbe-201a3d056e0c/2099851d-cf0a-4ee1-88b3-c99442d2551b/-M8KiaokwAS2Bk2O9ee5u_E5HLY.jpg",
        "url": "https://www.cars.com/vehicledetail/fa769e21-a137-4f03-bcdf-7f919e4719d5/",
        "dealRating": null,
        "cleanTitle": true,
        "noAccidents": true,
        "source": "cars.com"
      },
      {
        "id": "d8ef5f09-eb2f-4fd2-83ae-c7eea05881cd",
        "year": 2004,
        "make": "Audi",
        "model": "A4",
        "trim": "1.8T Cabriolet",
        "price": 9950,
        "mileage": 45587,
        "location": "Feasterville-Trevose, PA",
        "distanceMi": 28,
        "dealer": "Car Cheer",
        "imageUrl": "https://platform.cstatic-images.com/large/in/v2/a733be78-f490-4868-adbe-201a3d056e0c/73978ca8-644e-4561-9459-7f22e426ea7e/azPniDeNgOeCRg9cn8mKoQU3188.jpg",
        "url": "https://www.cars.com/vehicledetail/d8ef5f09-eb2f-4fd2-83ae-c7eea05881cd/",
        "dealRating": null,
        "cleanTitle": true,
        "noAccidents": true,
        "source": "cars.com"
      },
      {
        "id": "5c0a3f27-cf27-478a-aca3-831f460bb905",
        "year": 2002,
        "make": "Mercedes-Benz",
        "model": "CLK-Class",
        "trim": "430 Cabriolet",
        "price": 9990,
        "mileage": 27598,
        "location": "Sanatoga, PA",
        "distanceMi": 24,
        "dealer": "HiLine Motorsports LLC",
        "imageUrl": "https://platform.cstatic-images.com/large/in/v2/d2d2dd17-63b8-5f2d-9b51-a7318875f847/f4e3e29a-5fb6-4eeb-a977-c0f2745aedf3/n8w2vTVwt303vU-xQmp36IV8BKw.jpg",
        "url": "https://www.cars.com/vehicledetail/5c0a3f27-cf27-478a-aca3-831f460bb905/",
        "dealRating": null,
        "cleanTitle": true,
        "noAccidents": true,
        "source": "cars.com"
      },
      {
        "id": "cd816b0e-1e8d-49ac-ad3f-1b24c05a50c3",
        "year": 2000,
        "make": "BMW",
        "model": "Z3",
        "trim": "2.3 Roadster",
        "price": 9990,
        "mileage": 75828,
        "location": "Willow Grove, PA",
        "distanceMi": 23,
        "dealer": "Selden Motors",
        "imageUrl": "https://platform.cstatic-images.com/large/in/v2/41500c3b-0278-565b-b8aa-8a53ec151e79/58b5e849-7ee3-4b18-a73c-d3cdf34c5bd6/160afUSZOApeW0JcGb2ZeOK-bgA.jpg",
        "url": "https://www.cars.com/vehicledetail/cd816b0e-1e8d-49ac-ad3f-1b24c05a50c3/",
        "dealRating": null,
        "cleanTitle": true,
        "noAccidents": true,
        "source": "cars.com"
      },
      {
        "id": "c822098f-4e48-4053-ac80-cac595d90b63",
        "year": 2011,
        "make": "BMW",
        "model": "128",
        "trim": "128i 2dr Convertible SULEV",
        "price": 9995,
        "mileage": 147552,
        "location": "Levittown, PA",
        "distanceMi": 35,
        "dealer": "Bristol Auto Mall",
        "imageUrl": "https://platform.cstatic-images.com/large/in/v2/66aedd22-5f4c-571c-bcc9-9a6e5d5a07c7/9ad95780-0702-412c-b31e-e44fa24094aa/VzajC8Oo11oD-uHgdt9QaZM7B48.jpg",
        "url": "https://www.cars.com/vehicledetail/c822098f-4e48-4053-ac80-cac595d90b63/",
        "dealRating": null,
        "cleanTitle": true,
        "noAccidents": true,
        "source": "cars.com"
      },
      {
        "id": "5ed8f0d0-e49e-4595-b40b-06db6328c2e1",
        "year": 2015,
        "make": "MINI",
        "model": "Convertible",
        "trim": "Cooper",
        "price": 9999,
        "mileage": 55000,
        "location": "Easttown, PA",
        "distanceMi": 8,
        "dealer": "Private seller: Jerry",
        "imageUrl": "https://platform.cstatic-images.com/large/in/v2/p2p/7c218327-0c22-43ec-ba78-96ef5e726111/519f581a-e182-4041-9b51-5ef13606b3b4.jpg",
        "url": "https://www.cars.com/vehicledetail/5ed8f0d0-e49e-4595-b40b-06db6328c2e1/",
        "dealRating": null,
        "cleanTitle": true,
        "noAccidents": true,
        "source": "cars.com"
      },
      {
        "id": "15ab7fb3-236c-47bc-baf5-c775e701d490",
        "year": 1994,
        "make": "Ford",
        "model": "Mustang",
        "trim": "GT",
        "price": 10500,
        "mileage": 44000,
        "location": "Eddington, PA",
        "distanceMi": 29,
        "dealer": "Private seller: Joseph",
        "imageUrl": "https://platform.cstatic-images.com/large/in/v2/p2p/9e815461-6dc3-4712-8c5b-23b8d83d3cf3/37ae3543-f590-449f-8be0-58d7dd71217a.JPG",
        "url": "https://www.cars.com/vehicledetail/15ab7fb3-236c-47bc-baf5-c775e701d490/",
        "dealRating": null,
        "cleanTitle": true,
        "noAccidents": true,
        "source": "cars.com"
      },
      {
        "id": "11a59567-1e64-4f4b-a04a-6708a153e1ad",
        "year": 1995,
        "make": "Jaguar",
        "model": "XJS",
        "trim": "2+2",
        "price": 10897,
        "mileage": 46103,
        "location": "Magnolia, NJ",
        "distanceMi": 21,
        "dealer": "Avi Auto Sales",
        "imageUrl": "https://platform.cstatic-images.com/large/in/v2/2a9ff44c-1d8c-572a-b85a-e2c017e560ce/eec71dc7-9fe7-4cbe-86f1-4f071ac06ac8/uDIu0L8GLJu1FM_qrVpDQjhb3kk.jpg",
        "url": "https://www.cars.com/vehicledetail/11a59567-1e64-4f4b-a04a-6708a153e1ad/",
        "dealRating": null,
        "cleanTitle": true,
        "noAccidents": true,
        "source": "cars.com"
      },
      {
        "id": "d108c4ab-9423-4d63-ba08-da5ad8a63615",
        "year": 2011,
        "make": "Volvo",
        "model": "C70",
        "trim": "T5",
        "price": 10990,
        "mileage": 93899,
        "location": "Vineland, NJ",
        "distanceMi": 35,
        "dealer": "JC MILLER AUTO SALES INC",
        "imageUrl": "https://platform.cstatic-images.com/large/in/v2/5ba3cb38-9313-46f4-bf2a-09e8e250c34b/0e18d3f1-3925-475f-904e-edc38e24e0f9/LQ1-JbzItZBIDWtQCVv91Sm5FZY.jpg",
        "url": "https://www.cars.com/vehicledetail/d108c4ab-9423-4d63-ba08-da5ad8a63615/",
        "dealRating": null,
        "cleanTitle": true,
        "noAccidents": true,
        "source": "cars.com"
      },
      {
        "id": "9fa3f6eb-7ef8-4a2e-90c7-e978ff2b8a79",
        "year": 2007,
        "make": "Audi",
        "model": "A4",
        "trim": "2.0T Cabriolet quattro",
        "price": 10990,
        "mileage": 62185,
        "location": "Willow Grove, PA",
        "distanceMi": 23,
        "dealer": "Selden Motors",
        "imageUrl": "https://platform.cstatic-images.com/large/in/v2/41500c3b-0278-565b-b8aa-8a53ec151e79/67c17dcd-1350-4c8a-8e3c-f91c251b9c4f/F6kI3u8dODREG2uu3pajYdPGx5I.jpg",
        "url": "https://www.cars.com/vehicledetail/9fa3f6eb-7ef8-4a2e-90c7-e978ff2b8a79/",
        "dealRating": null,
        "cleanTitle": true,
        "noAccidents": true,
        "source": "cars.com"
      },
      {
        "id": "ec9c89f9-e9f8-447f-af3f-a68f8a558ded",
        "year": 2007,
        "make": "Mercedes-Benz",
        "model": "SLK-Class",
        "trim": null,
        "price": 10999,
        "mileage": 95916,
        "location": "Westville, NJ",
        "distanceMi": 16,
        "dealer": "Broadway Auto Sales Inc.",
        "imageUrl": "https://platform.cstatic-images.com/large/in/v2/c7e01295-5d1a-5abf-b8b8-60c6266232b4/372054b3-15c1-4f1d-898e-61d353011830/LdqoQZoGexcTQkbSWApt56-CxLs.jpg",
        "url": "https://www.cars.com/vehicledetail/ec9c89f9-e9f8-447f-af3f-a68f8a558ded/",
        "dealRating": null,
        "cleanTitle": true,
        "noAccidents": true,
        "source": "cars.com"
      },
      {
        "id": "f6ac7651-a075-4ba8-a116-44620ea693b5",
        "year": 2005,
        "make": "Mercedes-Benz",
        "model": "SL-Class",
        "trim": "SL 500 2dr Convertible",
        "price": 11990,
        "mileage": 75367,
        "location": "Feasterville-Trevose, PA",
        "distanceMi": 27,
        "dealer": "Divan Auto Group",
        "imageUrl": "https://platform.cstatic-images.com/large/in/v2/14d97cc8-5119-5137-8594-a38c068e21f3/4d495a20-6698-47ae-96b3-f66d00a989c5/J2aRu--DHNlDsEqahlPcCVQy2p8.jpg",
        "url": "https://www.cars.com/vehicledetail/f6ac7651-a075-4ba8-a116-44620ea693b5/",
        "dealRating": null,
        "cleanTitle": true,
        "noAccidents": true,
        "source": "cars.com"
      },
      {
        "id": "168e7196-5cc3-49bb-8faf-622353175793",
        "year": 2013,
        "make": "Mercedes-Benz",
        "model": "E-Class",
        "trim": "E 350",
        "price": 11995,
        "mileage": 119433,
        "location": "Spring City, PA",
        "distanceMi": 20,
        "dealer": "Premier Motor Group",
        "imageUrl": "https://platform.cstatic-images.com/large/in/v2/687e2a1f-ebc7-5430-89f7-b9a52e6185f9/f3f63d52-5d12-42b0-98bb-b1240058acd8/aOEatydVFsvUrrSZ9U83SKz6byo.jpg",
        "url": "https://www.cars.com/vehicledetail/168e7196-5cc3-49bb-8faf-622353175793/",
        "dealRating": null,
        "cleanTitle": true,
        "noAccidents": true,
        "source": "cars.com"
      },
      {
        "id": "484e893b-06f5-4307-9b2c-6f7b6c0d93d2",
        "year": 2016,
        "make": "Audi",
        "model": "A3",
        "trim": "2.0T Premium",
        "price": 11999,
        "mileage": 83000,
        "location": "Whitemarsh, PA",
        "distanceMi": 16,
        "dealer": "Private seller: Justin",
        "imageUrl": "https://platform.cstatic-images.com/large/in/v2/p2p/0cb11156-d4b9-4b04-b292-c2f8153b0994/fab80809-9c21-407b-9cbb-ae374f36d811.JPG",
        "url": "https://www.cars.com/vehicledetail/484e893b-06f5-4307-9b2c-6f7b6c0d93d2/",
        "dealRating": null,
        "cleanTitle": true,
        "noAccidents": true,
        "source": "cars.com"
      },
      {
        "id": "2ef5601d-4f79-468e-835e-ccccfaea71e8",
        "year": 2012,
        "make": "Audi",
        "model": "S5",
        "trim": "3.0 Premium Plus",
        "price": 12000,
        "mileage": 91900,
        "location": "Cornwells Heights, PA",
        "distanceMi": 28,
        "dealer": "Driven Imports",
        "imageUrl": "https://platform.cstatic-images.com/large/in/v2/e38c73e1-af87-4f69-aaab-26acff7cbf95/f11b1101-2596-40e7-833d-2e81bcbd282d/6P60FbvLh8BPheQdVl2NKq6FuqA.jpg",
        "url": "https://www.cars.com/vehicledetail/2ef5601d-4f79-468e-835e-ccccfaea71e8/",
        "dealRating": null,
        "cleanTitle": true,
        "noAccidents": true,
        "source": "cars.com"
      },
      {
        "id": "4f0bd49c-c50a-493b-9143-0d0a13d0ee26",
        "year": 2012,
        "make": "Volkswagen",
        "model": "Eos",
        "trim": "Komfort",
        "price": 12385,
        "mileage": 76397,
        "location": "Downingtown, PA",
        "distanceMi": 16,
        "dealer": "Jeff D'Ambrosio Chrysler Dodge Jeep Mits",
        "imageUrl": "https://platform.cstatic-images.com/large/in/v2/12beb5a4-335b-5025-b9f6-2d0571f07634/68c7f4de-ea3b-408b-83aa-1321d3e9187f/1qIDU0jNIfOWDLqWmx4-YMJgcjQ.jpg",
        "url": "https://www.cars.com/vehicledetail/4f0bd49c-c50a-493b-9143-0d0a13d0ee26/",
        "dealRating": null,
        "cleanTitle": true,
        "noAccidents": true,
        "source": "cars.com"
      },
      {
        "id": "b41a5e26-55f9-4a2c-b660-ac147ad9232c",
        "year": 2016,
        "make": "Buick",
        "model": "Cascada",
        "trim": "Premium",
        "price": 12843,
        "mileage": 68342,
        "location": "Haddon Township, NJ",
        "distanceMi": 18,
        "dealer": "Royal Auto Group",
        "imageUrl": "https://platform.cstatic-images.com/large/in/v2/220992f4-6d7b-5a84-999a-0c3c413cdc94/7fff6d97-9734-4570-9835-bfcd6df58dcc/hBA-jltuW4eEo6d0vH4_ZNWymag.jpg",
        "url": "https://www.cars.com/vehicledetail/b41a5e26-55f9-4a2c-b660-ac147ad9232c/",
        "dealRating": null,
        "cleanTitle": true,
        "noAccidents": true,
        "source": "cars.com"
      },
      {
        "id": "f7d54151-c2eb-4bbb-a4f7-710d3cfe2836",
        "year": 2010,
        "make": "Lexus",
        "model": "IS",
        "trim": "250C Base",
        "price": 13450,
        "mileage": 124762,
        "location": "Norristown, PA",
        "distanceMi": 14,
        "dealer": "New Concept Inc",
        "imageUrl": "https://platform.cstatic-images.com/large/in/v2/5631252c-0139-5d87-8647-26d44957f0e7/d35e8904-3dc0-469b-9e8f-e5091f2e12a4/VOyBnZtgK6xfBPE7yxnVu8esqFs.jpg",
        "url": "https://www.cars.com/vehicledetail/f7d54151-c2eb-4bbb-a4f7-710d3cfe2836/",
        "dealRating": null,
        "cleanTitle": true,
        "noAccidents": true,
        "source": "cars.com"
      },
      {
        "id": "4287146b-e5a9-40b8-9ed9-713bcbcaed66",
        "year": 1997,
        "make": "Porsche",
        "model": "Boxster",
        "trim": "Base",
        "price": 13795,
        "mileage": 85050,
        "location": "Bensalem, PA",
        "distanceMi": 29,
        "dealer": "Meric Auto Group LLC",
        "imageUrl": "https://platform.cstatic-images.com/large/in/v2/73ea6201-0793-408c-8eb2-98f1ae413f64/7a76aec6-3f05-4eb4-a1e9-afef1a1d4328/raZuyTkxmh9-Z3JlG0b7VTIB1Kg.jpg",
        "url": "https://www.cars.com/vehicledetail/4287146b-e5a9-40b8-9ed9-713bcbcaed66/",
        "dealRating": null,
        "cleanTitle": true,
        "noAccidents": true,
        "source": "cars.com"
      },
      {
        "id": "a135b04b-731a-4970-9921-7b447abef746",
        "year": 2001,
        "make": "Jaguar",
        "model": "XK8",
        "trim": "Base",
        "price": 13950,
        "mileage": 48977,
        "location": "Feasterville-Trevose, PA",
        "distanceMi": 28,
        "dealer": "Car Cheer",
        "imageUrl": "https://platform.cstatic-images.com/large/in/v2/a733be78-f490-4868-adbe-201a3d056e0c/d9d085f5-2102-4b11-97da-3ac04f5c9fde/cAdgEHSE5lJkgAoJK7rm0yLuCeU.jpg",
        "url": "https://www.cars.com/vehicledetail/a135b04b-731a-4970-9921-7b447abef746/",
        "dealRating": null,
        "cleanTitle": true,
        "noAccidents": true,
        "source": "cars.com"
      },
      {
        "id": "51db27cb-cb76-4731-8f4e-5bf8e9789c48",
        "year": 2012,
        "make": "BMW",
        "model": "128",
        "trim": "128i",
        "price": 13995,
        "mileage": 58476,
        "location": "Spring City, PA",
        "distanceMi": 20,
        "dealer": "Premier Motor Group",
        "imageUrl": "https://platform.cstatic-images.com/large/in/v2/687e2a1f-ebc7-5430-89f7-b9a52e6185f9/631443ad-ce4c-4c42-a28d-b72759b5fb08/1PryllcHPcpWBcWD7I8TddPsDco.jpg",
        "url": "https://www.cars.com/vehicledetail/51db27cb-cb76-4731-8f4e-5bf8e9789c48/",
        "dealRating": null,
        "cleanTitle": true,
        "noAccidents": true,
        "source": "cars.com"
      },
      {
        "id": "3fc0ea70-f5f0-4387-8424-91a9f498928b",
        "year": 2004,
        "make": "BMW",
        "model": "M3",
        "trim": "Base",
        "price": 14900,
        "mileage": 143000,
        "location": "Gladwyne, PA",
        "distanceMi": 12,
        "dealer": "Private seller: neal",
        "imageUrl": "https://platform.cstatic-images.com/large/in/v2/p2p/a4ab0316-4fee-48be-973e-be0bd510023e/7fa249d7-1582-46c2-a306-24e1f2c06bc9",
        "url": "https://www.cars.com/vehicledetail/3fc0ea70-f5f0-4387-8424-91a9f498928b/",
        "dealRating": null,
        "cleanTitle": true,
        "noAccidents": true,
        "source": "cars.com"
      },
      {
        "id": "28e34a7e-8f68-4f08-9be6-ffb499508f57",
        "year": 2011,
        "make": "Volvo",
        "model": "C70",
        "trim": "T5",
        "price": 9995,
        "mileage": 74659,
        "location": "Collegeville, PA",
        "distanceMi": 19,
        "dealer": "Keyser & Miller Ford",
        "imageUrl": null,
        "url": "https://www.cars.com/vehicledetail/28e34a7e-8f68-4f08-9be6-ffb499508f57/",
        "dealRating": null,
        "cleanTitle": true,
        "noAccidents": true,
        "source": "cars.com"
      },
      {
        "id": "dabcb463-e945-41fc-b07c-dd08637d350a",
        "year": 2011,
        "make": "Audi",
        "model": "S5",
        "trim": "3.0 Premium Plus",
        "price": 13642,
        "mileage": 69156,
        "location": "Haddon Township, NJ",
        "distanceMi": 18,
        "dealer": "Royal Auto Group",
        "imageUrl": "https://platform.cstatic-images.com/large/in/v2/220992f4-6d7b-5a84-999a-0c3c413cdc94/564cee7d-5505-4712-8a54-7f364740f431/TWUJbSHF9Ip8hGWCmQukBmMLH-E.jpg",
        "url": "https://www.cars.com/vehicledetail/dabcb463-e945-41fc-b07c-dd08637d350a/",
        "dealRating": null,
        "cleanTitle": true,
        "noAccidents": true,
        "source": "cars.com"
      },
      {
        "id": "249a4f7a-793a-4433-a51f-7f20d703fe2b",
        "year": 2000,
        "make": "BMW",
        "model": "323",
        "trim": "CI",
        "price": 8700,
        "mileage": 112014,
        "location": "Hellertown, PA",
        "distanceMi": 46,
        "dealer": "J C L Automotive",
        "imageUrl": "https://platform.cstatic-images.com/large/in/v2/f4e7dc74-7ed1-524c-af36-33cc477b803e/721a4d16-a6f4-4462-80f8-acf741200a11/5UPSZHfdLkQZ4nHygAD20QnC5cQ.jpg",
        "url": "https://www.cars.com/vehicledetail/249a4f7a-793a-4433-a51f-7f20d703fe2b/",
        "dealRating": null,
        "cleanTitle": true,
        "noAccidents": true,
        "source": "cars.com"
      },
      {
        "id": "83869b92-bed6-4dda-b339-0fa9e7c5fdd3",
        "year": 2008,
        "make": "Saturn",
        "model": "Sky",
        "trim": "Roadster",
        "price": 9995,
        "mileage": 39382,
        "location": "Hamilton, NJ",
        "distanceMi": 44,
        "dealer": "J&S Autohaus III",
        "imageUrl": "https://platform.cstatic-images.com/large/in/v2/8285800d-eb23-508d-90f9-c5b41e407538/6dc3dbab-c16b-418d-8ff4-f939d9b54fd7/r30hyq33czsvRyiXOZEEai-nL7c.jpg",
        "url": "https://www.cars.com/vehicledetail/83869b92-bed6-4dda-b339-0fa9e7c5fdd3/",
        "dealRating": null,
        "cleanTitle": true,
        "noAccidents": true,
        "source": "cars.com"
      },
      {
        "id": "8727b093-35f7-4713-8d30-52b91603290d",
        "year": 2000,
        "make": "BMW",
        "model": "Z3",
        "trim": "2.3 Roadster",
        "price": 7799,
        "mileage": 82690,
        "location": "Bordentown, NJ",
        "distanceMi": 42,
        "dealer": "Independence Auto Sale",
        "imageUrl": "https://platform.cstatic-images.com/large/in/v2/b19182ae-668a-5e30-93ee-2b50a30a2c77/59fdf3e0-6a93-4f59-b698-e2d57c3f7eba/4XMaF_diNmpVbz9EM1ypQy2xWbk.jpg",
        "url": "https://www.cars.com/vehicledetail/8727b093-35f7-4713-8d30-52b91603290d/",
        "dealRating": null,
        "cleanTitle": true,
        "noAccidents": true,
        "source": "cars.com"
      }
    ]
  },
  "cargurus": {
    "totalFound": 19,
    "url": "https://www.cargurus.com/Cars/l-Used-Convertible-bg1?zip=19063&distance=35&minPrice=7000&maxPrice=15000",
    "listings": [
      {
        "id": "416443505",
        "year": 2018,
        "make": "Ford",
        "model": "Mustang",
        "trim": "EcoBoost Premium Convertible",
        "price": 13887,
        "mileage": 141767,
        "location": "Berlin, NJ",
        "distanceMi": 27,
        "dealRating": "Fair Deal",
        "imageUrl": "https://static.cargurus.com/images/forsale/2026/03/08/05/25/2018_ford_mustang-pic-8593394937171371335-1024x768.jpeg",
        "url": "https://www.cargurus.com/details/416443505",
        "dealer": null,
        "cleanTitle": null,
        "noAccidents": null,
        "source": "cargurus"
      },
      {
        "id": "445030972",
        "year": 2010,
        "make": "Lexus",
        "model": "IS",
        "trim": "250C Convertible",
        "price": 13815,
        "mileage": 124762,
        "location": "Norristown, PA",
        "distanceMi": 14,
        "dealRating": "Fair Deal",
        "imageUrl": "https://static.cargurus.com/images/forsale/2026/06/06/06/03/2010_lexus_is-pic-5588792168135260060-1024x768.jpeg",
        "url": "https://www.cargurus.com/details/445030972",
        "dealer": null,
        "cleanTitle": null,
        "noAccidents": null,
        "source": "cargurus"
      },
      {
        "id": "447408669",
        "year": 2011,
        "make": "Audi",
        "model": "S5",
        "trim": "3.0T quattro Prestige Cabriolet",
        "price": 14337,
        "mileage": 69156,
        "location": "Haddon Township, NJ",
        "distanceMi": 17,
        "dealRating": "Good Deal",
        "imageUrl": "https://static.cargurus.com/images/forsale/2026/05/06/23/37/2011_audi_s5-pic-3807763922415203099-1024x768.jpeg",
        "url": "https://www.cargurus.com/details/447408669",
        "dealer": null,
        "cleanTitle": null,
        "noAccidents": null,
        "source": "cargurus"
      },
      {
        "id": "433875732",
        "year": 2014,
        "make": "BMW",
        "model": "4 Series",
        "trim": "428i xDrive Convertible",
        "price": 10555,
        "mileage": 103444,
        "location": "Philadelphia, PA",
        "distanceMi": 19,
        "dealRating": "Good Deal",
        "imageUrl": "https://static.cargurus.com/images/forsale/2026/06/12/15/05/2014_bmw_4_series-pic-7438888840704462163-1024x768.jpeg",
        "url": "https://www.cargurus.com/details/433875732",
        "dealer": null,
        "cleanTitle": null,
        "noAccidents": null,
        "source": "cargurus"
      },
      {
        "id": "450126370",
        "year": 2016,
        "make": "Buick",
        "model": "Cascada",
        "trim": "Premium",
        "price": 13538,
        "mileage": 68342,
        "location": "Haddon Township, NJ",
        "distanceMi": 17,
        "dealRating": "Good Deal",
        "imageUrl": "https://static.cargurus.com/images/forsale/2026/06/05/19/23/2016_buick_cascada-pic-893023158311408492-1024x768.jpeg",
        "url": "https://www.cargurus.com/details/450126370",
        "dealer": null,
        "cleanTitle": null,
        "noAccidents": null,
        "source": "cargurus"
      },
      {
        "id": "450252850",
        "year": 2011,
        "make": "Volvo",
        "model": "C70",
        "trim": "T5",
        "price": 10485,
        "mileage": 74659,
        "location": "Collegeville, PA",
        "distanceMi": 18,
        "dealRating": "Fair Deal",
        "imageUrl": "https://static.cargurus.com/images/forsale/2026/06/20/00/33/2011_volvo_c70-pic-4169063936498010816-1024x768.jpeg",
        "url": "https://www.cargurus.com/details/450252850",
        "dealer": null,
        "cleanTitle": null,
        "noAccidents": null,
        "source": "cargurus"
      },
      {
        "id": "418683572",
        "year": 2012,
        "make": "Mercedes-Benz",
        "model": "SLK",
        "trim": "250",
        "price": 13438,
        "mileage": 64249,
        "location": "Haddon Township, NJ",
        "distanceMi": 17,
        "dealRating": "Good Deal",
        "imageUrl": "https://static.cargurus.com/images/forsale/2025/07/02/01/25/2012_mercedes-benz_slk-pic-605218941275330186-1024x768.jpeg",
        "url": "https://www.cargurus.com/details/418683572",
        "dealer": null,
        "cleanTitle": null,
        "noAccidents": null,
        "source": "cargurus"
      },
      {
        "id": "447819611",
        "year": 2007,
        "make": "Saab",
        "model": "9-3",
        "trim": "Aero Convertible",
        "price": 11496,
        "mileage": 81323,
        "location": "Wilmington, DE",
        "distanceMi": 14,
        "dealRating": "Good Deal",
        "imageUrl": "https://static.cargurus.com/images/forsale/2026/05/27/06/05/2007_saab_9-3-pic-5308153467144029579-1024x768.jpeg",
        "url": "https://www.cargurus.com/details/447819611",
        "dealer": null,
        "cleanTitle": null,
        "noAccidents": null,
        "source": "cargurus"
      },
      {
        "id": "450741160",
        "year": 2012,
        "make": "BMW",
        "model": "1 Series",
        "trim": "128i Convertible",
        "price": 14369,
        "mileage": 58476,
        "location": "Spring City, PA",
        "distanceMi": 19,
        "dealRating": "Fair Deal",
        "imageUrl": "https://static.cargurus.com/images/forsale/2026/06/17/21/36/2012_bmw_1_series-pic-5415289025991728862-1024x768.jpeg",
        "url": "https://www.cargurus.com/details/450741160",
        "dealer": null,
        "cleanTitle": null,
        "noAccidents": null,
        "source": "cargurus"
      },
      {
        "id": "443962216",
        "year": 2014,
        "make": "Volkswagen",
        "model": "Beetle",
        "trim": "2.5L Convertible",
        "price": 9200,
        "mileage": 127956,
        "location": "Maple Shade, NJ",
        "distanceMi": 23,
        "dealRating": "Good Deal",
        "imageUrl": "https://static.cargurus.com/images/forsale/2026/05/21/10/16/2014_volkswagen_beetle-pic-889656598920584541-1024x768.jpeg",
        "url": "https://www.cargurus.com/details/443962216",
        "dealer": null,
        "cleanTitle": null,
        "noAccidents": null,
        "source": "cargurus"
      },
      {
        "id": "447787678",
        "year": 2014,
        "make": "Nissan",
        "model": "Murano CrossCabriolet",
        "trim": "AWD",
        "price": 9342,
        "mileage": 97107,
        "location": "Gilbertsville, PA",
        "distanceMi": 29,
        "dealRating": "Good Deal",
        "imageUrl": "https://static.cargurus.com/images/forsale/2026/06/08/05/33/2014_nissan_murano_crosscabriolet-pic-35340187767206375-1024x768.jpeg",
        "url": "https://www.cargurus.com/details/447787678",
        "dealer": null,
        "cleanTitle": null,
        "noAccidents": null,
        "source": "cargurus"
      },
      {
        "id": "443733420",
        "year": 2014,
        "make": "Chevrolet",
        "model": "Camaro",
        "trim": "2LT Convertible",
        "price": 12995,
        "mileage": 104897,
        "location": "Levittown, PA",
        "distanceMi": 34,
        "dealRating": "Fair Deal",
        "imageUrl": "https://static.cargurus.com/images/forsale/2026/03/29/00/26/2014_chevrolet_camaro-pic-4934534250890962309-1024x768.jpeg",
        "url": "https://www.cargurus.com/details/443733420",
        "dealer": null,
        "cleanTitle": null,
        "noAccidents": null,
        "source": "cargurus"
      },
      {
        "id": "450151448",
        "year": 2014,
        "make": "MINI",
        "model": "Roadster",
        "trim": "S",
        "price": 11750,
        "mileage": 68527,
        "location": "Willow Grove, PA",
        "distanceMi": 23,
        "dealRating": "Fair Deal",
        "imageUrl": "https://static.cargurus.com/images/forsale/2026/06/05/22/23/2014_mini_roadster-pic-8333090666186309161-1024x768.jpeg",
        "url": "https://www.cargurus.com/details/450151448",
        "dealer": null,
        "cleanTitle": null,
        "noAccidents": null,
        "source": "cargurus"
      },
      {
        "id": "451367312",
        "year": 2010,
        "make": "BMW",
        "model": "3 Series",
        "trim": "328i Convertible",
        "price": 10900,
        "mileage": 80232,
        "location": "West Chester, PA",
        "distanceMi": 9,
        "dealRating": "Fair Deal",
        "imageUrl": "https://static.cargurus.com/images/forsale/2026/06/20/14/22/2010_bmw_3_series-pic-2956539671150296942-1024x768.jpeg",
        "url": "https://www.cargurus.com/details/451367312",
        "dealer": null,
        "cleanTitle": null,
        "noAccidents": null,
        "source": "cargurus"
      },
      {
        "id": "451390660",
        "year": 2011,
        "make": "Chrysler",
        "model": "200",
        "trim": "Limited Convertible",
        "price": 8995,
        "mileage": 81090,
        "location": "Jenkintown, PA",
        "distanceMi": 20,
        "dealRating": "Good Deal",
        "imageUrl": null,
        "url": "https://www.cargurus.com/details/451390660",
        "dealer": null,
        "cleanTitle": null,
        "noAccidents": null,
        "source": "cargurus"
      },
      {
        "id": "450947442",
        "year": 2011,
        "make": "BMW",
        "model": "1 Series",
        "trim": "128i Convertible",
        "price": 11485,
        "mileage": 50140,
        "location": "Doylestown, PA",
        "distanceMi": 33,
        "dealRating": "Good Deal",
        "imageUrl": null,
        "url": "https://www.cargurus.com/details/450947442",
        "dealer": null,
        "cleanTitle": null,
        "noAccidents": null,
        "source": "cargurus"
      },
      {
        "id": "445737422",
        "year": 2012,
        "make": "Ford",
        "model": "Mustang",
        "trim": "V6 Convertible",
        "price": 11459,
        "mileage": 96539,
        "location": "West Chester, PA",
        "distanceMi": 9,
        "dealRating": "Fair Deal",
        "imageUrl": "https://static.cargurus.com/images/forsale/2026/04/30/14/23/2012_ford_mustang-pic-2949931544508764713-1024x768.jpeg",
        "url": "https://www.cargurus.com/details/445737422",
        "dealer": null,
        "cleanTitle": null,
        "noAccidents": null,
        "source": "cargurus"
      },
      {
        "id": "447270039",
        "year": 2007,
        "make": "MINI",
        "model": "Cooper",
        "trim": "S Convertible",
        "price": 8942,
        "mileage": 65594,
        "location": "Gilbertsville, PA",
        "distanceMi": 29,
        "dealRating": "Fair Deal",
        "imageUrl": "https://static.cargurus.com/images/forsale/2026/05/08/05/34/2007_mini_cooper-pic-2043758708695550607-1024x768.jpeg",
        "url": "https://www.cargurus.com/details/447270039",
        "dealer": null,
        "cleanTitle": null,
        "noAccidents": null,
        "source": "cargurus"
      },
      {
        "id": "447818606",
        "year": 2014,
        "make": "Ford",
        "model": "Mustang",
        "trim": "V6 Premium Convertible",
        "price": 12499,
        "mileage": 79243,
        "location": "Delran, NJ",
        "distanceMi": 25,
        "dealRating": "Good Deal",
        "imageUrl": "https://static.cargurus.com/images/forsale/2026/05/12/04/26/2014_ford_mustang-pic-8260476369541184152-1024x768.jpeg",
        "url": "https://www.cargurus.com/details/447818606",
        "dealer": null,
        "cleanTitle": null,
        "noAccidents": null,
        "source": "cargurus"
      }
    ]
  },
  "autotrader": {
    "totalFound": 49,
    "url": "https://www.autotrader.com/cars-for-sale/all-cars/convertible/media-pa?minPrice=7000&maxPrice=15000&searchRadius=35&zip=19063&sortBy=derivedpriceASC",
    "listings": [
      {
        "id": "777627150",
        "year": 2015,
        "make": "MINI",
        "model": "Cooper",
        "trim": "Convertible",
        "price": 7495,
        "mileage": 118000,
        "distanceMi": 25,
        "dealer": "PA AUTO LIQUIDATORS LLC",
        "noAccidents": true,
        "url": "https://www.autotrader.com/cars-for-sale/vehicle/777627150",
        "location": null,
        "dealRating": null,
        "cleanTitle": null,
        "imageUrl": null,
        "source": "autotrader"
      },
      {
        "id": "775917821",
        "year": 2000,
        "make": "BMW",
        "model": "Z3",
        "trim": "2.8",
        "price": 7940,
        "mileage": 75000,
        "distanceMi": 15,
        "dealer": "Private Seller Exchange",
        "noAccidents": true,
        "url": "https://www.autotrader.com/cars-for-sale/vehicle/775917821",
        "location": null,
        "dealRating": null,
        "cleanTitle": null,
        "imageUrl": null,
        "source": "autotrader"
      },
      {
        "id": "783355105",
        "year": 1994,
        "make": "Ford",
        "model": "Mustang",
        "trim": "GT",
        "price": 7995,
        "mileage": 44000,
        "distanceMi": 27,
        "dealer": "CarNu Sales",
        "noAccidents": null,
        "url": "https://www.autotrader.com/cars-for-sale/vehicle/783355105",
        "location": null,
        "dealRating": null,
        "cleanTitle": null,
        "imageUrl": null,
        "source": "autotrader"
      },
      {
        "id": "778854923",
        "year": 2007,
        "make": "MINI",
        "model": "Cooper",
        "trim": "S",
        "price": 8452,
        "mileage": 65000,
        "distanceMi": 29,
        "dealer": "Josie's Auto Sales",
        "noAccidents": true,
        "url": "https://www.autotrader.com/cars-for-sale/vehicle/778854923",
        "location": null,
        "dealRating": null,
        "cleanTitle": null,
        "imageUrl": null,
        "source": "autotrader"
      },
      {
        "id": "754834213",
        "year": 2015,
        "make": "BMW",
        "model": "435i xDrive",
        "trim": "Convertible",
        "price": 8500,
        "mileage": 140000,
        "distanceMi": 27,
        "dealer": "Private Seller Exchange",
        "noAccidents": null,
        "url": "https://www.autotrader.com/cars-for-sale/vehicle/754834213",
        "location": null,
        "dealRating": null,
        "cleanTitle": null,
        "imageUrl": null,
        "source": "autotrader"
      },
      {
        "id": "783590664",
        "year": 2011,
        "make": "Chrysler",
        "model": "200",
        "trim": "Limited",
        "price": 8995,
        "mileage": 81000,
        "distanceMi": 20,
        "dealer": "Bryner Chevrolet",
        "noAccidents": null,
        "url": "https://www.autotrader.com/cars-for-sale/vehicle/783590664",
        "location": null,
        "dealRating": null,
        "cleanTitle": null,
        "imageUrl": null,
        "source": "autotrader"
      },
      {
        "id": "776291796",
        "year": 2014,
        "make": "Volkswagen",
        "model": "Beetle",
        "trim": "2.5",
        "price": 9200,
        "mileage": 127000,
        "distanceMi": 22,
        "dealer": "AMERICAN AUTO GROUP LLC",
        "noAccidents": true,
        "url": "https://www.autotrader.com/cars-for-sale/vehicle/776291796",
        "location": null,
        "dealRating": null,
        "cleanTitle": null,
        "imageUrl": null,
        "source": "autotrader"
      },
      {
        "id": "774459255",
        "year": 1997,
        "make": "Toyota",
        "model": "Paseo",
        "trim": "Convertible",
        "price": 9388,
        "mileage": 158000,
        "distanceMi": 17,
        "dealer": "Blue Bell Motorcars",
        "noAccidents": true,
        "url": "https://www.autotrader.com/cars-for-sale/vehicle/774459255",
        "location": null,
        "dealRating": null,
        "cleanTitle": null,
        "imageUrl": null,
        "source": "autotrader"
      },
      {
        "id": "777472503",
        "year": 2012,
        "make": "MINI",
        "model": "Cooper",
        "trim": "S",
        "price": 9400,
        "mileage": 98000,
        "distanceMi": 17,
        "dealer": "Private Seller Exchange",
        "noAccidents": true,
        "url": "https://www.autotrader.com/cars-for-sale/vehicle/777472503",
        "location": null,
        "dealRating": null,
        "cleanTitle": null,
        "imageUrl": null,
        "source": "autotrader"
      },
      {
        "id": "779702455",
        "year": 2004,
        "make": "BMW",
        "model": "Z4",
        "trim": "2.5i",
        "price": 9499,
        "mileage": 88000,
        "distanceMi": 16,
        "dealer": "Mainline Auto LLC",
        "noAccidents": true,
        "url": "https://www.autotrader.com/cars-for-sale/vehicle/779702455",
        "location": null,
        "dealRating": null,
        "cleanTitle": null,
        "imageUrl": null,
        "source": "autotrader"
      },
      {
        "id": "777348725",
        "year": 2002,
        "make": "Lexus",
        "model": "SC 430",
        "trim": "Convertible",
        "price": 9500,
        "mileage": 123000,
        "distanceMi": 29,
        "dealer": "Josie's Auto Sales",
        "noAccidents": true,
        "url": "https://www.autotrader.com/cars-for-sale/vehicle/777348725",
        "location": null,
        "dealRating": null,
        "cleanTitle": null,
        "imageUrl": null,
        "source": "autotrader"
      },
      {
        "id": "767240100",
        "year": 1989,
        "make": "Chevrolet",
        "model": "Corvette",
        "trim": "Convertible",
        "price": 9952,
        "mileage": 51000,
        "distanceMi": 29,
        "dealer": "Josie's Auto Sales",
        "noAccidents": true,
        "url": "https://www.autotrader.com/cars-for-sale/vehicle/767240100",
        "location": null,
        "dealRating": null,
        "cleanTitle": null,
        "imageUrl": null,
        "source": "autotrader"
      },
      {
        "id": "776363458",
        "year": 2002,
        "make": "Ford",
        "model": "Thunderbird",
        "trim": null,
        "price": 9952,
        "mileage": 114000,
        "distanceMi": 29,
        "dealer": "Josie's Auto Sales",
        "noAccidents": true,
        "url": "https://www.autotrader.com/cars-for-sale/vehicle/776363458",
        "location": null,
        "dealRating": null,
        "cleanTitle": null,
        "imageUrl": null,
        "source": "autotrader"
      },
      {
        "id": "775293866",
        "year": 2003,
        "make": "Lexus",
        "model": "SC 430",
        "trim": "Convertible",
        "price": 9952,
        "mileage": 184000,
        "distanceMi": 29,
        "dealer": "Josie's Auto Sales",
        "noAccidents": true,
        "url": "https://www.autotrader.com/cars-for-sale/vehicle/775293866",
        "location": null,
        "dealRating": null,
        "cleanTitle": null,
        "imageUrl": null,
        "source": "autotrader"
      },
      {
        "id": "770808740",
        "year": 2000,
        "make": "BMW",
        "model": "Z3",
        "trim": "2.5i",
        "price": 9990,
        "mileage": 75000,
        "distanceMi": 22,
        "dealer": "Selden Motors",
        "noAccidents": true,
        "url": "https://www.autotrader.com/cars-for-sale/vehicle/770808740",
        "location": null,
        "dealRating": null,
        "cleanTitle": null,
        "imageUrl": null,
        "source": "autotrader"
      },
      {
        "id": "697567405",
        "year": 2002,
        "make": "Mercedes-Benz",
        "model": "CLK 430",
        "trim": "Cabriolet",
        "price": 9990,
        "mileage": 27000,
        "distanceMi": 24,
        "dealer": "Hiline Motorsports LLC",
        "noAccidents": true,
        "url": "https://www.autotrader.com/cars-for-sale/vehicle/697567405",
        "location": null,
        "dealRating": null,
        "cleanTitle": null,
        "imageUrl": null,
        "source": "autotrader"
      },
      {
        "id": "774295178",
        "year": 2011,
        "make": "BMW",
        "model": "128i",
        "trim": "Convertible",
        "price": 9995,
        "mileage": 147000,
        "distanceMi": 34,
        "dealer": "Bristol Auto Mall",
        "noAccidents": true,
        "url": "https://www.autotrader.com/cars-for-sale/vehicle/774295178",
        "location": null,
        "dealRating": null,
        "cleanTitle": null,
        "imageUrl": null,
        "source": "autotrader"
      },
      {
        "id": "782465549",
        "year": 2011,
        "make": "Volvo",
        "model": "C70",
        "trim": "T5",
        "price": 10485,
        "mileage": 74000,
        "distanceMi": 19,
        "dealer": "Keyser Miller Ford",
        "noAccidents": true,
        "url": "https://www.autotrader.com/cars-for-sale/vehicle/782465549",
        "location": null,
        "dealRating": null,
        "cleanTitle": null,
        "imageUrl": null,
        "source": "autotrader"
      },
      {
        "id": "759302951",
        "year": 1995,
        "make": "Ford",
        "model": "Mustang",
        "trim": "GT",
        "price": 10495,
        "mileage": 55000,
        "distanceMi": 25,
        "dealer": "GT Motors, Inc.",
        "noAccidents": true,
        "url": "https://www.autotrader.com/cars-for-sale/vehicle/759302951",
        "location": null,
        "dealRating": null,
        "cleanTitle": null,
        "imageUrl": null,
        "source": "autotrader"
      },
      {
        "id": "724093944",
        "year": 1995,
        "make": "Jaguar",
        "model": "XJS",
        "trim": "4.0 Convertible",
        "price": 10497,
        "mileage": 46000,
        "distanceMi": 21,
        "dealer": "Avi Auto Sales",
        "noAccidents": true,
        "url": "https://www.autotrader.com/cars-for-sale/vehicle/724093944",
        "location": null,
        "dealRating": null,
        "cleanTitle": null,
        "imageUrl": null,
        "source": "autotrader"
      },
      {
        "id": "781593445",
        "year": 2010,
        "make": "BMW",
        "model": "328i",
        "trim": "Convertible",
        "price": 10900,
        "mileage": 80000,
        "distanceMi": 9,
        "dealer": "Sky Motor Cars",
        "noAccidents": null,
        "url": "https://www.autotrader.com/cars-for-sale/vehicle/781593445",
        "location": null,
        "dealRating": null,
        "cleanTitle": null,
        "imageUrl": null,
        "source": "autotrader"
      },
      {
        "id": "775464369",
        "year": 1989,
        "make": "Chevrolet",
        "model": "Corvette",
        "trim": "Convertible",
        "price": 10900,
        "mileage": 53000,
        "distanceMi": 29,
        "dealer": "Josie's Auto Sales",
        "noAccidents": true,
        "url": "https://www.autotrader.com/cars-for-sale/vehicle/775464369",
        "location": null,
        "dealRating": null,
        "cleanTitle": null,
        "imageUrl": null,
        "source": "autotrader"
      },
      {
        "id": "780320408",
        "year": 2012,
        "make": "Mazda",
        "model": "MX-5 Miata",
        "trim": "Grand Touring",
        "price": 10950,
        "mileage": 177000,
        "distanceMi": 20,
        "dealer": "Dera-Lee Auto Company",
        "noAccidents": null,
        "url": "https://www.autotrader.com/cars-for-sale/vehicle/780320408",
        "location": null,
        "dealRating": null,
        "cleanTitle": null,
        "imageUrl": null,
        "source": "autotrader"
      },
      {
        "id": "779890992",
        "year": 2007,
        "make": "Audi",
        "model": "A4",
        "trim": "2.0T",
        "price": 10990,
        "mileage": 62000,
        "distanceMi": 22,
        "dealer": "Selden Motors",
        "noAccidents": true,
        "url": "https://www.autotrader.com/cars-for-sale/vehicle/779890992",
        "location": null,
        "dealRating": null,
        "cleanTitle": null,
        "imageUrl": null,
        "source": "autotrader"
      },
      {
        "id": "779404347",
        "year": 2001,
        "make": "Porsche",
        "model": "Boxster",
        "trim": null,
        "price": 11250,
        "mileage": 74000,
        "distanceMi": 11,
        "dealer": "Private Seller Exchange",
        "noAccidents": true,
        "url": "https://www.autotrader.com/cars-for-sale/vehicle/779404347",
        "location": null,
        "dealRating": null,
        "cleanTitle": null,
        "imageUrl": null,
        "source": "autotrader"
      },
      {
        "id": "783198687",
        "year": 2011,
        "make": "BMW",
        "model": "128i",
        "trim": "Convertible",
        "price": 11485,
        "mileage": 50000,
        "distanceMi": 33,
        "dealer": "Fred Beans Genesis of Doylestown",
        "noAccidents": null,
        "url": "https://www.autotrader.com/cars-for-sale/vehicle/783198687",
        "location": null,
        "dealRating": null,
        "cleanTitle": null,
        "imageUrl": null,
        "source": "autotrader"
      },
      {
        "id": "691838857",
        "year": 2013,
        "make": "BMW",
        "model": "328i",
        "trim": "Convertible",
        "price": 11500,
        "mileage": 144000,
        "distanceMi": 29,
        "dealer": "Josie's Auto Sales",
        "noAccidents": null,
        "url": "https://www.autotrader.com/cars-for-sale/vehicle/691838857",
        "location": null,
        "dealRating": null,
        "cleanTitle": null,
        "imageUrl": null,
        "source": "autotrader"
      },
      {
        "id": "782391385",
        "year": 2014,
        "make": "MINI",
        "model": "Cooper Roadster",
        "trim": "S",
        "price": 11750,
        "mileage": 68000,
        "distanceMi": 22,
        "dealer": "Dealer",
        "noAccidents": null,
        "url": "https://www.autotrader.com/cars-for-sale/vehicle/782391385",
        "location": null,
        "dealRating": null,
        "cleanTitle": null,
        "imageUrl": null,
        "source": "autotrader"
      },
      {
        "id": "758394780",
        "year": 2012,
        "make": "BMW",
        "model": "650i xDrive",
        "trim": "Convertible",
        "price": 11895,
        "mileage": 106000,
        "distanceMi": 29,
        "dealer": "MERIC AUTO GROUP LLC",
        "noAccidents": null,
        "url": "https://www.autotrader.com/cars-for-sale/vehicle/758394780",
        "location": null,
        "dealRating": null,
        "cleanTitle": null,
        "imageUrl": null,
        "source": "autotrader"
      },
      {
        "id": "780042870",
        "year": 2013,
        "make": "MINI",
        "model": "Cooper Roadster",
        "trim": null,
        "price": 11969,
        "mileage": 75000,
        "distanceMi": 32,
        "dealer": "Thompson BMW",
        "noAccidents": null,
        "url": "https://www.autotrader.com/cars-for-sale/vehicle/780042870",
        "location": null,
        "dealRating": null,
        "cleanTitle": null,
        "imageUrl": null,
        "source": "autotrader"
      },
      {
        "id": "754018786",
        "year": 2005,
        "make": "Mercedes-Benz",
        "model": "SL 500",
        "trim": null,
        "price": 11990,
        "mileage": 75000,
        "distanceMi": 27,
        "dealer": "Divan Auto Group",
        "noAccidents": null,
        "url": "https://www.autotrader.com/cars-for-sale/vehicle/754018786",
        "location": null,
        "dealRating": null,
        "cleanTitle": null,
        "imageUrl": null,
        "source": "autotrader"
      },
      {
        "id": "780080978",
        "year": 2007,
        "make": "Saab",
        "model": "9-3",
        "trim": "Aero",
        "price": 11991,
        "mileage": 81000,
        "distanceMi": 14,
        "dealer": "Audi Wilmington",
        "noAccidents": null,
        "url": "https://www.autotrader.com/cars-for-sale/vehicle/780080978",
        "location": null,
        "dealRating": null,
        "cleanTitle": null,
        "imageUrl": null,
        "source": "autotrader"
      },
      {
        "id": "780885942",
        "year": 2013,
        "make": "Mercedes-Benz",
        "model": "E 350",
        "trim": "Cabriolet",
        "price": 11995,
        "mileage": 119000,
        "distanceMi": 20,
        "dealer": "Premier Motor Group",
        "noAccidents": null,
        "url": "https://www.autotrader.com/cars-for-sale/vehicle/780885942",
        "location": null,
        "dealRating": null,
        "cleanTitle": null,
        "imageUrl": null,
        "source": "autotrader"
      },
      {
        "id": "777620700",
        "year": 2004,
        "make": "Lexus",
        "model": "SC 430",
        "trim": "Convertible",
        "price": 11995,
        "mileage": 152000,
        "distanceMi": 28,
        "dealer": "LEGACY USED AUTO LLC",
        "noAccidents": null,
        "url": "https://www.autotrader.com/cars-for-sale/vehicle/777620700",
        "location": null,
        "dealRating": null,
        "cleanTitle": null,
        "imageUrl": null,
        "source": "autotrader"
      },
      {
        "id": "778587840",
        "year": 2013,
        "make": "Volvo",
        "model": "C70",
        "trim": "T5",
        "price": 12270,
        "mileage": 124000,
        "distanceMi": 21,
        "dealer": "EXTREME AUTO CARE",
        "noAccidents": null,
        "url": "https://www.autotrader.com/cars-for-sale/vehicle/778587840",
        "location": null,
        "dealRating": null,
        "cleanTitle": null,
        "imageUrl": null,
        "source": "autotrader"
      },
      {
        "id": "782756492",
        "year": 2012,
        "make": "Volkswagen",
        "model": "Eos",
        "trim": "Komfort",
        "price": 12385,
        "mileage": 76000,
        "distanceMi": 16,
        "dealer": "Jeff D'Ambrosio's Dodge Chrysler Jeep",
        "noAccidents": null,
        "url": "https://www.autotrader.com/cars-for-sale/vehicle/782756492",
        "location": null,
        "dealRating": null,
        "cleanTitle": null,
        "imageUrl": null,
        "source": "autotrader"
      },
      {
        "id": "754357433",
        "year": 2002,
        "make": "Ford",
        "model": "Thunderbird",
        "trim": null,
        "price": 12395,
        "mileage": 54000,
        "distanceMi": 25,
        "dealer": "GT Motors, Inc.",
        "noAccidents": null,
        "url": "https://www.autotrader.com/cars-for-sale/vehicle/754357433",
        "location": null,
        "dealRating": null,
        "cleanTitle": null,
        "imageUrl": null,
        "source": "autotrader"
      },
      {
        "id": "768877215",
        "year": 2002,
        "make": "Toyota",
        "model": "MR2",
        "trim": null,
        "price": 12500,
        "mileage": 56000,
        "distanceMi": 16,
        "dealer": "Private Seller Exchange",
        "noAccidents": null,
        "url": "https://www.autotrader.com/cars-for-sale/vehicle/768877215",
        "location": null,
        "dealRating": null,
        "cleanTitle": null,
        "imageUrl": null,
        "source": "autotrader"
      },
      {
        "id": "782476875",
        "year": 1997,
        "make": "Chevrolet",
        "model": "Camaro",
        "trim": "Z28",
        "price": 12795,
        "mileage": 73000,
        "distanceMi": 29,
        "dealer": "",
        "noAccidents": null,
        "url": "https://www.autotrader.com/cars-for-sale/vehicle/782476875",
        "location": null,
        "dealRating": null,
        "cleanTitle": null,
        "imageUrl": null,
        "source": "autotrader"
      },
      {
        "id": "783468945",
        "year": 1995,
        "make": "Chevrolet",
        "model": "Camaro",
        "trim": "Z28",
        "price": 12900,
        "mileage": 119000,
        "distanceMi": 19,
        "dealer": "",
        "noAccidents": null,
        "url": "https://www.autotrader.com/cars-for-sale/vehicle/783468945",
        "location": null,
        "dealRating": null,
        "cleanTitle": null,
        "imageUrl": null,
        "source": "autotrader"
      },
      {
        "id": "774473437",
        "year": 2018,
        "make": "Ford",
        "model": "Mustang",
        "trim": "Premium",
        "price": 12992,
        "mileage": 141000,
        "distanceMi": 26,
        "dealer": "",
        "noAccidents": null,
        "url": "https://www.autotrader.com/cars-for-sale/vehicle/774473437",
        "location": null,
        "dealRating": null,
        "cleanTitle": null,
        "imageUrl": null,
        "source": "autotrader"
      },
      {
        "id": "776106189",
        "year": 2014,
        "make": "Chevrolet",
        "model": "Camaro",
        "trim": "LT",
        "price": 12995,
        "mileage": 104000,
        "distanceMi": 34,
        "dealer": "",
        "noAccidents": null,
        "url": "https://www.autotrader.com/cars-for-sale/vehicle/776106189",
        "location": null,
        "dealRating": null,
        "cleanTitle": null,
        "imageUrl": null,
        "source": "autotrader"
      },
      {
        "id": "780558350",
        "year": 2001,
        "make": "Porsche",
        "model": "Boxster",
        "trim": null,
        "price": 13498,
        "mileage": 106000,
        "distanceMi": 30,
        "dealer": "",
        "noAccidents": null,
        "url": "https://www.autotrader.com/cars-for-sale/vehicle/780558350",
        "location": null,
        "dealRating": null,
        "cleanTitle": null,
        "imageUrl": null,
        "source": "autotrader"
      },
      {
        "id": "780096191",
        "year": 1997,
        "make": "Porsche",
        "model": "Boxster",
        "trim": null,
        "price": 13795,
        "mileage": 85000,
        "distanceMi": 29,
        "dealer": "",
        "noAccidents": null,
        "url": "https://www.autotrader.com/cars-for-sale/vehicle/780096191",
        "location": null,
        "dealRating": null,
        "cleanTitle": null,
        "imageUrl": null,
        "source": "autotrader"
      },
      {
        "id": "678637598",
        "year": 2002,
        "make": "Lexus",
        "model": "SC 430",
        "trim": "Convertible",
        "price": 13952,
        "mileage": 113000,
        "distanceMi": 29,
        "dealer": "",
        "noAccidents": null,
        "url": "https://www.autotrader.com/cars-for-sale/vehicle/678637598",
        "location": null,
        "dealRating": null,
        "cleanTitle": null,
        "imageUrl": null,
        "source": "autotrader"
      },
      {
        "id": "782950781",
        "year": 2012,
        "make": "BMW",
        "model": "128i",
        "trim": "Convertible",
        "price": 13995,
        "mileage": 58000,
        "distanceMi": 20,
        "dealer": "",
        "noAccidents": null,
        "url": "https://www.autotrader.com/cars-for-sale/vehicle/782950781",
        "location": null,
        "dealRating": null,
        "cleanTitle": null,
        "imageUrl": null,
        "source": "autotrader"
      },
      {
        "id": "781637429",
        "year": 2003,
        "make": "Mercedes-Benz",
        "model": "SL 500",
        "trim": null,
        "price": 14000,
        "mileage": 63000,
        "distanceMi": 29,
        "dealer": "",
        "noAccidents": null,
        "url": "https://www.autotrader.com/cars-for-sale/vehicle/781637429",
        "location": null,
        "dealRating": null,
        "cleanTitle": null,
        "imageUrl": null,
        "source": "autotrader"
      },
      {
        "id": "782985814",
        "year": 1999,
        "make": "Mercedes-Benz",
        "model": "SLK 230",
        "trim": null,
        "price": 14500,
        "mileage": 69000,
        "distanceMi": 12,
        "dealer": "",
        "noAccidents": null,
        "url": "https://www.autotrader.com/cars-for-sale/vehicle/782985814",
        "location": null,
        "dealRating": null,
        "cleanTitle": null,
        "imageUrl": null,
        "source": "autotrader"
      },
      {
        "id": "783074697",
        "year": 2015,
        "make": "INFINITI",
        "model": "Q60",
        "trim": "Convertible",
        "price": 14513,
        "mileage": 108000,
        "distanceMi": 20,
        "dealer": "",
        "noAccidents": null,
        "url": "https://www.autotrader.com/cars-for-sale/vehicle/783074697",
        "location": null,
        "dealRating": null,
        "cleanTitle": null,
        "imageUrl": null,
        "source": "autotrader"
      }
    ]
  },
  "truecar": {
    "totalFound": 0,
    "url": "https://www.truecar.com/used-cars-for-sale/listings/convertible/?zip=19063",
    "listings": []
  },
  "top10": {
    "introHtml": "<p>Ranked for a cheap fun second car \u2014 condition and reliability first, mileage flexible. These 10 picks span the best values across all three sources as of today's refresh.</p>",
    "picks": [
      {
        "rank": 1,
        "year": 2000,
        "make": "BMW",
        "model": "Z3",
        "trim": "2.8",
        "price": 7940,
        "mileage": 75000,
        "location": null,
        "distanceMi": 15,
        "dealer": "Private Seller Exchange",
        "source": "autotrader",
        "url": "https://www.autotrader.com/cars-for-sale/vehicle/775917821",
        "dealRating": null,
        "imageUrl": null,
        "whyGood": "BMW Z3 2.8 is the sweet spot of the Z3 range \u2014 the 6-cylinder inline engine delivers smooth power and a distinctive exhaust note. 75k miles is modest for an E36-era Z3, which can go 200k+ with basic maintenance. Private seller at $7,940 is well below market. Only 15 miles away.",
        "whatToVerify": "Full top operation cycle. Check for water in footwells (drain plugs clog). Rear plastic window for cloudiness/cracks. Rocker panel and floor rust. Timing chain rattle on cold start. Cooling system maintenance history (plastic components age).",
        "bottomLine": "Best-value Z3 in the search \u2014 right engine, right mileage, right price, close by."
      },
      {
        "rank": 2,
        "year": 2015,
        "make": "BMW",
        "model": "435i xDrive",
        "trim": "Convertible",
        "price": 8500,
        "mileage": 140000,
        "location": null,
        "distanceMi": 27,
        "dealer": "Private Seller Exchange",
        "source": "autotrader",
        "url": "https://www.autotrader.com/cars-for-sale/vehicle/754834213",
        "dealRating": null,
        "imageUrl": null,
        "whyGood": "2015 BMW 435i xDrive Convertible at $8,500 is exceptional value for a modern turbocharged grand tourer with AWD. The N55 turbo inline-6 makes 300hp. Clean title at this price for a modern BMW is a calculated risk, but F33 Bimmers are solid if maintained.",
        "whatToVerify": "Full hardtop retractable mechanism (full cycle, check seal leaks). Water intrusion in trunk (drainage tubes clog). Oil consumption. Coolant system. Water pump and thermostat service. CarFax for service history. DSC/iDrive warning lights.",
        "bottomLine": "Modern turbocharged BMW grand tourer convertible at entry-level price \u2014 exceptional if mechanically sound."
      },
      {
        "rank": 3,
        "year": 2004,
        "make": "Audi",
        "model": "A4",
        "trim": "1.8T Cabriolet",
        "price": 9950,
        "mileage": 45587,
        "location": "Feasterville-Trevose, PA",
        "distanceMi": 28,
        "dealer": "Car Cheer",
        "source": "cars.com",
        "url": "https://www.cars.com/vehicledetail/d8ef5f09-eb2f-4fd2-83ae-c7eea05881cd/",
        "dealRating": null,
        "imageUrl": "https://platform.cstatic-images.com/large/in/v2/a733be78-f490-4868-adbe-201a3d056e0c/73978ca8-644e-4561-9459-7f22e426ea7e/azPniDeNgOeCRg9cn8mKoQU3188.jpg",
        "whyGood": "Only 45,587 miles on a 2004 Audi A4 Cabriolet is extraordinary. The 1.8T engine is proven and tuneable. Cars.com verified clean title and no accidents. At $9,950 for sub-50k miles this is an excellent deal.",
        "whatToVerify": "Top operation (full cycle). Timing belt service history \u2014 critical on 1.8T. Oil sludge check (common on 1.8T with neglected oil changes). Soft top seams and rear window condition. Door seal leaks.",
        "bottomLine": "45k-mile Audi A4 Cabriolet is the standout low-mileage find in this search."
      },
      {
        "rank": 4,
        "year": 2010,
        "make": "BMW",
        "model": "3 Series",
        "trim": "328i Convertible",
        "price": 10900,
        "mileage": 80232,
        "location": "West Chester, PA",
        "distanceMi": 9,
        "dealer": "Sky Motor Cars",
        "source": "cargurus",
        "url": "https://www.cargurus.com/details/451367312",
        "dealRating": "Fair Deal",
        "imageUrl": "https://static.cargurus.com/images/forsale/2026/06/20/14/22/2010_bmw_3_series-pic-2956539671150296942-1024x768.jpeg",
        "whyGood": "2010 E93 328i Convertible at 80k miles, only 9 miles away. The E93 has a proper folding hardtop, exceptional build quality, and the N52 inline-6 is one of BMW's most reliable naturally-aspirated engines. $10,900 is fair for a clean 80k-mile E93.",
        "whatToVerify": "Full hardtop folding mechanism (hydraulic rams, check for leaks). Roof seals on all four corners. N52 VANOS rattle on startup. Coolant system service. Oil leaks from valve cover. Water damage to rear seat area.",
        "bottomLine": "Clean low-mileage E93 hardtop convertible 9 miles away \u2014 the practical choice."
      },
      {
        "rank": 5,
        "year": 2011,
        "make": "BMW",
        "model": "1 Series",
        "trim": "128i Convertible",
        "price": 11485,
        "mileage": 50140,
        "location": "Doylestown, PA",
        "distanceMi": 33,
        "dealer": null,
        "source": "cargurus",
        "url": "https://www.cargurus.com/details/450947442",
        "dealRating": "Good Deal",
        "imageUrl": null,
        "whyGood": "50k miles on a 2011 BMW 128i Convertible is exceptional. The 128i's N52 inline-6 is supremely reliable. CarGurus rates it a Good Deal. Half the miles of comparable listings at $11,485.",
        "whatToVerify": "Full soft-top operation. Rear window delamination. N52 VANOS rattle on cold start. Subframe cracks (known E82/E88 weak point). Coolant expansion tank condition. Interior leak test after rain.",
        "bottomLine": "Half the mileage of comparable 128i listings at a fair price \u2014 excellent reliability prospect."
      },
      {
        "rank": 6,
        "year": 2002,
        "make": "Mercedes-Benz",
        "model": "CLK-Class",
        "trim": "430 Cabriolet",
        "price": 9990,
        "mileage": 27598,
        "location": "Sanatoga, PA",
        "distanceMi": 24,
        "dealer": "HiLine Motorsports LLC",
        "source": "cars.com",
        "url": "https://www.cars.com/vehicledetail/5c0a3f27-cf27-478a-aca3-831f460bb905/",
        "dealRating": null,
        "imageUrl": "https://platform.cstatic-images.com/large/in/v2/d2d2dd17-63b8-5f2d-9b51-a7318875f847/f4e3e29a-5fb6-4eeb-a977-c0f2745aedf3/n8w2vTVwt303vU-xQmp36IV8BKw.jpg",
        "whyGood": "27,598 miles is the lowest mileage in the entire dataset. The CLK430 Cabriolet's 4.3L V8 is smooth and powerful. Cars.com verified clean title and no accidents. Under $10k for a time-capsule V8 Cabriolet.",
        "whatToVerify": "Top hydraulic pump operation and all four locks. All weather seals. Rust (especially if stored outside). Age-related rubber seals. Window regulators, SRS sensor faults. Odometer fraud check \u2014 verify authentic low miles.",
        "bottomLine": "27k miles on a V8 Cabriolet is the rarest find in this search \u2014 verify the odometer and buy it."
      },
      {
        "rank": 7,
        "year": 2007,
        "make": "MINI",
        "model": "Cooper",
        "trim": "S Convertible",
        "price": 8942,
        "mileage": 65594,
        "location": "Gilbertsville, PA",
        "distanceMi": 29,
        "dealer": "Josie's Auto Sales",
        "source": "cargurus",
        "url": "https://www.cargurus.com/details/447270039",
        "dealRating": "Fair Deal",
        "imageUrl": "https://static.cargurus.com/images/forsale/2026/05/08/05/34/2007_mini_cooper-pic-2043758708695550607-1024x768.jpeg",
        "whyGood": "2007 MINI Cooper S Convertible with 65k miles under $9k. The S's supercharged 1.6L makes 172hp and is genuinely entertaining. 65k is young for a well-maintained MINI. Simple R52 soft-top design.",
        "whatToVerify": "Supercharger belt condition and whine. Top operation including rear window zip. Oil leaks. Power steering pump condition. Coolant temp behavior. Interior water damage at door sills. Timing chain tensioner history.",
        "bottomLine": "Low-mileage MINI S Convertible under $9k \u2014 sporty, simple top, good value."
      },
      {
        "rank": 8,
        "year": 2011,
        "make": "Chrysler",
        "model": "200",
        "trim": "Limited Convertible",
        "price": 8995,
        "mileage": 81090,
        "location": "Jenkintown, PA",
        "distanceMi": 20,
        "dealer": null,
        "source": "cargurus",
        "url": "https://www.cargurus.com/details/451390660",
        "dealRating": "Good Deal",
        "imageUrl": null,
        "whyGood": "2011 Chrysler 200 Limited Convertible rated Good Deal at $8,995. 81k miles is moderate. Simple, proven soft-top. Limited trim adds leather. Good entry-level drop-top for pure cruising value.",
        "whatToVerify": "Full top operation through complete cycle. Top fabric condition and rear window delamination. Rear-seat water damage. Top motor reliability \u2014 check for slow/hesitant operation. Transmission shudder check.",
        "bottomLine": "Reliable, comfortable entry-level convertible with solid CarGurus deal rating at a fair price."
      },
      {
        "rank": 9,
        "year": 2012,
        "make": "Ford",
        "model": "Mustang",
        "trim": "V6 Convertible",
        "price": 11459,
        "mileage": 96539,
        "location": "West Chester, PA",
        "distanceMi": 9,
        "dealer": null,
        "source": "cargurus",
        "url": "https://www.cargurus.com/details/445737422",
        "dealRating": "Fair Deal",
        "imageUrl": "https://static.cargurus.com/images/forsale/2026/04/30/14/23/2012_ford_mustang-pic-2949931544508764713-1024x768.jpeg",
        "whyGood": "2012 Mustang V6 Convertible at 9 miles from Media. S197 V6 (305hp) is genuinely fun and more fuel-efficient than the GT. Under 100k miles for $11,459 is solid Mustang value.",
        "whatToVerify": "Full soft-top operation and seal condition. Rear seat water intrusion. S197 rear IRS clunk. T5 third-gear synchro. 8.8 rear axle clunk. Convertible top mount rust at rocker junction.",
        "bottomLine": "Local V6 Mustang convertible under 100k at a fair price \u2014 easy to check out and buy."
      },
      {
        "rank": 10,
        "year": 2001,
        "make": "Porsche",
        "model": "Boxster",
        "trim": null,
        "price": 11250,
        "mileage": 74000,
        "location": null,
        "distanceMi": 11,
        "dealer": "Private Seller Exchange",
        "source": "autotrader",
        "url": "https://www.autotrader.com/cars-for-sale/vehicle/779404347",
        "dealRating": null,
        "imageUrl": null,
        "whyGood": "2001 Porsche Boxster at 74k miles and $11,250. Mid-engine layout and balance unmatched in this price range. No-accidents verified. 11 miles away for easy inspection.",
        "whatToVerify": "IMS bearing service is the critical item \u2014 verify documented IMS upgrade or factor in cost. RMS oil leak check. Top operation including latches and hydraulic struts. Water in footwells (drainage tubes). Coolant leaks. Pull codes for limp-mode issues.",
        "bottomLine": "Mid-engine Porsche sports car under $12k \u2014 thrilling if IMS bearing is documented."
      }
    ]
  },
  "mustangs": {
    "totalFound": 5,
    "introHtml": "<p>All Ford Mustang convertibles found within the search area, ranked by trim and value. SN-95 5.0 GT models top the list for V8 character; the S197 V6 wins on practicality and proximity.</p>",
    "picks": [
      {
        "rank": 1,
        "year": 1994,
        "make": "Ford",
        "model": "Mustang",
        "trim": "GT",
        "price": 10500,
        "mileage": 44000,
        "location": "Eddington, PA",
        "distanceMi": 29,
        "dealer": "Private seller: Joseph",
        "source": "cars.com",
        "url": "https://www.cars.com/vehicledetail/15ab7fb3-236c-47bc-baf5-c775e701d490/",
        "dealRating": null,
        "imageUrl": "https://platform.cstatic-images.com/large/in/v2/p2p/9e815461-6dc3-4712-8c5b-23b8d83d3cf3/37ae3543-f590-449f-8be0-58d7dd71217a.JPG",
        "whyGood": "44k original miles on a 1994 GT convertible from a private seller \u2014 last year of the 5.0 V8. Cars.com verified clean title and no accidents.",
        "whatToVerify": "SN-95 convertible frame rust at top-mount-to-rocker junction. Full top operation. 5.0 oil pressure and cooling. Rear axle clunk. T5 shift quality. Floor pan rust inspection.",
        "bottomLine": "Last of the 5.0 SN-95 GT convertibles with only 44k miles \u2014 a true collector-grade find."
      },
      {
        "rank": 2,
        "year": 1994,
        "make": "Ford",
        "model": "Mustang",
        "trim": "GT",
        "price": 7995,
        "mileage": 44000,
        "location": null,
        "distanceMi": 27,
        "dealer": "CarNu Sales",
        "source": "autotrader",
        "url": "https://www.autotrader.com/cars-for-sale/vehicle/783355105",
        "dealRating": null,
        "imageUrl": null,
        "whyGood": "Another 1994 GT with 44k miles at only $7,995 \u2014 significantly cheaper than the Cars.com example. Same low-mileage SN-95 GT appeal at a bargain price.",
        "whatToVerify": "Same SN-95 checklist: frame rust at convertible top mounts, 5.0 V8 health, T5 transmission, floor pan rust. Verify top mechanism and fabric condition.",
        "bottomLine": "Budget SN-95 GT at $7,995 with 44k miles \u2014 compelling value if condition checks out."
      },
      {
        "rank": 3,
        "year": 1995,
        "make": "Ford",
        "model": "Mustang",
        "trim": "GT",
        "price": 10495,
        "mileage": 55000,
        "location": null,
        "distanceMi": 25,
        "dealer": "GT Motors, Inc.",
        "source": "autotrader",
        "url": "https://www.autotrader.com/cars-for-sale/vehicle/759302951",
        "dealRating": null,
        "imageUrl": null,
        "whyGood": "1995 GT convertible with 55k miles \u2014 still 5.0L V8. No-accidents verified. $10,495 from a specialty Mustang dealer.",
        "whatToVerify": "Same SN-95 checklist. Confirm 5.0 is original. Timing chain and oil pressure. Usual SN-95 frame rust points.",
        "bottomLine": "Low-mileage 5.0 GT from a Mustang specialist \u2014 strong option with implied expertise."
      },
      {
        "rank": 4,
        "year": 2012,
        "make": "Ford",
        "model": "Mustang",
        "trim": "V6 Convertible",
        "price": 11459,
        "mileage": 96539,
        "location": "West Chester, PA",
        "distanceMi": 9,
        "dealer": null,
        "source": "cargurus",
        "url": "https://www.cargurus.com/details/445737422",
        "dealRating": "Fair Deal",
        "imageUrl": "https://static.cargurus.com/images/forsale/2026/04/30/14/23/2012_ford_mustang-pic-2949931544508764713-1024x768.jpeg",
        "whyGood": "Modern S197 V6 (305hp) at 9 miles from Media. Under 100k miles at $11,459. Easy local test drive.",
        "whatToVerify": "S197 rear frame rust at top mount. Soft top and rear window. IRS clunk. T5/6-speed shift quality. Rear seat water staining.",
        "bottomLine": "The practical modern Mustang convertible \u2014 fast V6, close by, reasonable mileage."
      },
      {
        "rank": 5,
        "year": 2014,
        "make": "Ford",
        "model": "Mustang",
        "trim": "V6 Premium Convertible",
        "price": 12499,
        "mileage": 79243,
        "location": "Delran, NJ",
        "distanceMi": 25,
        "dealer": null,
        "source": "cargurus",
        "url": "https://www.cargurus.com/details/447818606",
        "dealRating": "Good Deal",
        "imageUrl": "https://static.cargurus.com/images/forsale/2026/05/12/04/26/2014_ford_mustang-pic-8260476369541184152-1024x768.jpeg",
        "whyGood": "2014 V6 Premium Convertible at 79k miles with CarGurus Good Deal rating and $500 price drop. Premium trim with Sync and Shaker audio. Last S197 before the S550 redesign.",
        "whatToVerify": "Same S197 checklist. Rear seat water staining from top seal. Sync and premium electronics function. No SRS codes.",
        "bottomLine": "Late S197 Premium with Good Deal rating and recent price drop \u2014 well-equipped and under budget."
      }
    ]
  }
}